odoo/addons/ssi_sequence_mixin/README.rst
odoo/addons/ssi_sequence_mixin/__init__.py
odoo/addons/ssi_sequence_mixin/__manifest__.py
odoo/addons/ssi_sequence_mixin/menu.xml
odoo/addons/ssi_sequence_mixin/i18n/ssi_sequence_mixin.pot
odoo/addons/ssi_sequence_mixin/models/__init__.py
odoo/addons/ssi_sequence_mixin/models/mixin_sequence.py
odoo/addons/ssi_sequence_mixin/models/sequence_template.py
odoo/addons/ssi_sequence_mixin/security/ir.model.access.csv
odoo/addons/ssi_sequence_mixin/static/description/icon.png
odoo/addons/ssi_sequence_mixin/static/description/index.html
odoo/addons/ssi_sequence_mixin/static/img/bug.png
odoo/addons/ssi_sequence_mixin/static/img/circuit.png
odoo/addons/ssi_sequence_mixin/static/img/download.png
odoo/addons/ssi_sequence_mixin/static/img/info.png
odoo/addons/ssi_sequence_mixin/static/img/medal.png
odoo/addons/ssi_sequence_mixin/static/img/questions.png
odoo/addons/ssi_sequence_mixin/static/img/workflow.png
odoo/addons/ssi_sequence_mixin/tests/__init__.py
odoo/addons/ssi_sequence_mixin/tests/base.py
odoo/addons/ssi_sequence_mixin/tests/dummy_model.py
odoo/addons/ssi_sequence_mixin/tests/scenario_custom_prefix.yml
odoo/addons/ssi_sequence_mixin/tests/scenario_custom_prefix_suffix.yml
odoo/addons/ssi_sequence_mixin/tests/scenario_custom_suffix.yml
odoo/addons/ssi_sequence_mixin/tests/test_custom_prefix.py
odoo/addons/ssi_sequence_mixin/tests/test_custom_prefix_suffix.py
odoo/addons/ssi_sequence_mixin/tests/test_custom_suffix.py
odoo/addons/ssi_sequence_mixin/tests/test_mixin_sequence.py
odoo/addons/ssi_sequence_mixin/views/sequence_template_views.xml
odoo_addon_ssi_sequence_mixin-18.0.1.1.0.dist-info/METADATA
odoo_addon_ssi_sequence_mixin-18.0.1.1.0.dist-info/WHEEL
odoo_addon_ssi_sequence_mixin-18.0.1.1.0.dist-info/top_level.txt
odoo_addon_ssi_sequence_mixin-18.0.1.1.0.dist-info/RECORD
